NifiLibrary/NifiLibraryKeywords.py
NifiLibrary/__init__.py
NifiLibrary/version.py
tests/__init__.py
tests/test_nifi_token.py
tests/test_parameter.py
tests/test_process_group.py
tests/test_processor.py
robotframework_nifilibrary-2.1.4.dist-info/METADATA
robotframework_nifilibrary-2.1.4.dist-info/WHEEL
robotframework_nifilibrary-2.1.4.dist-info/top_level.txt
robotframework_nifilibrary-2.1.4.dist-info/RECORD
