Metadata-Version: 2.1
Name: robotframework-nifilibrary
Version: 2.1.4
Summary: Nifi library for robotframework
Home-page: 
Author: Weeraporn.pai
Author-email: weeraporn.pa@gmail.com
License: MIT
Classifier: Development Status :: 3 - Alpha
Classifier: Intended Audience :: Developers
Classifier: Topic :: Software Development :: Testing
Classifier: License :: OSI Approved :: MIT License
Classifier: Programming Language :: Python :: 3
Classifier: Operating System :: OS Independent
Classifier: Programming Language :: Python
Classifier: Programming Language :: Python :: 3
Classifier: Programming Language :: Python :: 3.5
Classifier: Programming Language :: Python :: 3.6
Classifier: Programming Language :: Python :: 3.7
Requires-Dist: requests >=2.31.0
Requires-Dist: robotframework >=3.2.2
Requires-Dist: nipyapi ==0.20.0
Requires-Dist: pytest-cov ==2.12.1
Requires-Dist: pytest ==8.3.2
Requires-Dist: codecov ==2.1.13
